nc_api/__init__.py
nc_scp_api-0.0.4.dist-info/LICENSE
nc_scp_api-0.0.4.dist-info/METADATA
nc_scp_api-0.0.4.dist-info/WHEEL
nc_scp_api-0.0.4.dist-info/top_level.txt
nc_scp_api-0.0.4.dist-info/RECORD
