Metadata-Version: 2.1
Name: nc-scp-api
Version: 0.0.4
Summary: API wrapper for the netcup scp api
Home-page: https://github.com/jdenda/nc_scp_api
Author: Janneck Denda
Author-email: j@denda.dev
License: UNKNOWN
Platform: UNKNOWN
Classifier: Programming Language :: Python :: 3
Classifier: License :: OSI Approved :: GNU General Public License v3 (GPLv3)
Classifier: Operating System :: OS Independent
Requires-Python: >=3.6
Requires-Dist: suds-py3
